RegexRewriter/RegexRewriter.py
RegexRewriter/__init__.py
RegexRewriter-0.1.1.dist-info/LICENSE
RegexRewriter-0.1.1.dist-info/METADATA
RegexRewriter-0.1.1.dist-info/WHEEL
RegexRewriter-0.1.1.dist-info/top_level.txt
RegexRewriter-0.1.1.dist-info/RECORD
