Metadata-Version: 2.2
Name: RegexRewriter
Version: 0.1.1
Home-page: https://github.com/SIGMazer/RegexRewriter
Author: Mazin Sayed (SIGMazer)
Author-email: Mazinasd7@gamil.com   
Classifier: Programming Language :: Python :: 3
Classifier: License :: OSI Approved :: MIT License
Classifier: Operating System :: OS Independent
Requires-Python: >=3.6
License-File: LICENSE
Dynamic: author
Dynamic: author-email
Dynamic: classifier
Dynamic: description
Dynamic: description-content-type
Dynamic: home-page
Dynamic: requires-python
